ms_querytool.py
ms_querytool-1.2.dist-info/LICENSE.txt
ms_querytool-1.2.dist-info/METADATA
ms_querytool-1.2.dist-info/WHEEL
ms_querytool-1.2.dist-info/top_level.txt
ms_querytool-1.2.dist-info/RECORD
