Metadata-Version: 2.1
Name: ms-querytool
Version: 1.2
Summary: Tool to ingest a SQL txt file, run all of the statements, and return the results
Home-page: UNKNOWN
Author: Marc Stumbo
Author-email: marc.stumbo@verizonwireless.com
License: MS
Platform: UNKNOWN
Requires-Python: >3
